{"id": 223, "doc": [{"name": "AUSTRALIAN COLONIES GOVERNMENT BILL", "date": "1850-03-22", "year": 1850, "token": 35064, "count": 2276}, {"name": "AUSTRALIAN COLONIES GOVERNMENT BILL", "date": "1850-04-19", "year": 1850, "token": 26691, "count": 1477}, {"name": "HOUSE OF LORDS", "date": "1907-06-24", "year": 1907, "token": 39666, "count": 1287}, {"name": "HOUSE OF LORDS", "date": "1907-06-25", "year": 1907, "token": 36888, "count": 1265}, {"name": "HOUSE OF LORDS", "date": "1907-06-26", "year": 1907, "token": 40498, "count": 1039}, {"name": "AUSTRALIAN COLONIES GOVERNMENT BILL", "date": "1850-02-18", "year": 1850, "token": 18794, "count": 964}, {"name": "GOVERNMENT OF IRELAND BILL No ", "date": "1893-05-10", "year": 1893, "token": 20968, "count": 906}, {"name": "LEGISLATIVE COUNCIL CANADA BILL", "date": "1854-06-29", "year": 1854, "token": 19178, "count": 863}, {"name": "THE AUSTRALIAN COLONIES COMMITTEE", "date": "1850-02-08", "year": 1850, "token": 18494, "count": 797}, {"name": "AUSTRALIAN COLONIES GOVERNMENT BILL", "date": "1850-06-11", "year": 1850, "token": 15363, "count": 766}, {"name": "AUSTRALIAN COLONIES GOVERNMENT BILL", "date": "1850-05-13", "year": 1850, "token": 17259, "count": 722}, {"name": "JAMAICA GOVERNMENT BILL", "date": "1839-05-03", "year": 1839, "token": 40737, "count": 716}, {"name": "NEW ZEALAND GOVERNMENT BILL", "date": "1848-02-14", "year": 1848, "token": 18186, "count": 596}, {"name": "JAMAICA SUSPENSION OF THE CONSTITUTION ADJOURNED DEBATE", "date": "1839-05-06", "year": 1839, "token": 39122, "count": 595}, {"name": "STATE OF THE REPRESENTATION", "date": "1817-05-20", "year": 1817, "token": 43774, "count": 593}, {"name": "AUSTRALIAN COLONIES GOVERNMENT BILL", "date": "1850-05-31", "year": 1850, "token": 12761, "count": 529}, {"name": "REPRESENTATIVE GOVERNMENT", "date": "1889-05-17", "year": 1889, "token": 20591, "count": 524}, {"name": "AUSTRALIAN COLONIES GOVERNMENT BILL", "date": "1850-05-06", "year": 1850, "token": 28100, "count": 463}, {"name": "FOREIGN AFFAIRS RESOLUTIONS", "date": "1849-07-20", "year": 1849, "token": 44374, "count": 461}, {"name": "CANADA", "date": "1837-04-14", "year": 1837, "token": 32635, "count": 460}, {"name": "NEW ZEALAND GOVERNMENT BILL", "date": "1852-06-04", "year": 1852, "token": 19095, "count": 456}, {"name": "LEGISLATIVE COUNCIL CANADA BILL", "date": "1854-08-04", "year": 1854, "token": 9192, "count": 450}, {"name": "SECOND READING SECOND NIGHT", "date": "1861-05-16", "year": 1861, "token": 38232, "count": 448}, {"name": "AUSTRALIAN COLONIES GOVERNMENT BILL", "date": "1850-06-10", "year": 1850, "token": 14567, "count": 433}, {"name": "PARLIAMENTARY REFORM BILL FOR ENGLAND THIRD READING ADJOURNED DEBATE", "date": "1831-09-21", "year": 1831, "token": 34371, "count": 428}, {"name": "NEW ZEALAND GOVERNMENT BILL", "date": "1852-05-21", "year": 1852, "token": 24821, "count": 418}, {"name": "MOTION RELATING TO THE TRANSFER OF GENOA", "date": "1815-04-27", "year": 1815, "token": 24294, "count": 415}, {"name": "CHURCH OF SCOTLAND", "date": "1843-03-07", "year": 1843, "token": 27791, "count": 411}, {"name": "REFORM OF PARLIAMENT", "date": "1822-04-25", "year": 1822, "token": 35245, "count": 411}, {"name": "HOUSE OF LORDS RESOLUTION", "date": "1888-03-09", "year": 1888, "token": 19806, "count": 405}, {"name": "TRANSVAAL AND ORANGE RIVER COLONIES CONSTITUTIONS", "date": "1906-12-17", "year": 1906, "token": 28393, "count": 402}, {"name": "CANADA ADJOURNED DEBATE", "date": "1838-01-23", "year": 1838, "token": 45694, "count": 399}, {"name": "NEWSPAPER STAMP DUTIES BILL", "date": "1819-12-20", "year": 1819, "token": 21759, "count": 388}, {"name": "CLASS II", "date": "1906-07-31", "year": 1906, "token": 27839, "count": 379}, {"name": "RESOLUTION", "date": "1879-05-13", "year": 1879, "token": 32910, "count": 378}, {"name": "AUSTRALIAN COLONIES BILL", "date": "1850-04-22", "year": 1850, "token": 15205, "count": 370}, {"name": "PARLIAMENTARY REFORM BILL FOR ENGLAND THIRD READING AD JOURNED DEBATE", "date": "1831-09-20", "year": 1831, "token": 35556, "count": 356}, {"name": "CANADA", "date": "1838-01-25", "year": 1838, "token": 27177, "count": 352}, {"name": "MOTION FOR A SELECT COMMITTEE", "date": "1888-03-19", "year": 1888, "token": 21886, "count": 352}, {"name": "COMMITTEE Progress th May", "date": "1893-05-16", "year": 1893, "token": 29973, "count": 349}, {"name": "PARLIAMENTARY REFORM BILL FOR ENGLAND THIRD READING", "date": "1831-09-19", "year": 1831, "token": 34363, "count": 341}, {"name": "KINGS SPEECH MOTION FOR AN ADDRESS", "date": "1907-02-18", "year": 1907, "token": 37089, "count": 338}, {"name": "AFFAIRS OF POLAND", "date": "1833-07-09", "year": 1833, "token": 27668, "count": 334}, {"name": "NEGOTIATIONS RELATIVE TO SPAIN", "date": "1823-04-24", "year": 1823, "token": 31600, "count": 329}, {"name": "CORPORATION REFORM LORDS AMENDMENTS", "date": "1835-08-31", "year": 1835, "token": 22410, "count": 326}, {"name": "PRIVILEGE LORD WENSLEYDALES PATENT PEERAGES FOR LIFE", "date": "1856-02-07", "year": 1856, "token": 49358, "count": 324}, {"name": "COMMITTEE Progress th May", "date": "1983-05-09", "year": 1893, "token": 27303, "count": 317}, {"name": "PAPERS MOVED FOR", "date": "1863-05-12", "year": 1863, "token": 10795, "count": 315}, {"name": "COMMONWEALTH OF AUSTRALIA CONSTITUTION BILL", "date": "1900-05-21", "year": 1900, "token": 18465, "count": 313}, {"name": "PRIVILEGE STOCKDALE v HANSARD", "date": "1840-01-20", "year": 1840, "token": 40923, "count": 312}, {"name": "COLONIAL ADMINISTRATION", "date": "1849-04-16", "year": 1849, "token": 25511, "count": 310}, {"name": "AFFAIRS OF CANADA", "date": "1837-03-06", "year": 1837, "token": 30324, "count": 309}, {"name": "NEW ZEALAND GOVERNMENT", "date": "1852-05-03", "year": 1852, "token": 15093, "count": 309}, {"name": "NAPLES CONDUCT OF THE ALLIED POWEKS", "date": "1821-02-21", "year": 1821, "token": 22624, "count": 308}, {"name": "IONIAN ISLANDS", "date": "1822-05-14", "year": 1822, "token": 13792, "count": 307}, {"name": "PARLIAMENTARY REFORM BILL  COMMITTEE", "date": "1831-04-18", "year": 1831, "token": 21022, "count": 307}, {"name": "ADDRESS FOR CORRESPONDENCE", "date": "1863-04-17", "year": 1863, "token": 10352, "count": 305}, {"name": "PARLIAMENTARY REFORM BILL FOR ENGLAND LORDS AMENDMENTS", "date": "1832-06-05", "year": 1832, "token": 21331, "count": 305}, {"name": "MOTION FOR PAPERS", "date": "1866-03-20", "year": 1866, "token": 8196, "count": 301}, {"name": "RESOLUTION", "date": "1877-06-28", "year": 1877, "token": 14448, "count": 299}, {"name": "PARLIAMENTARY REFORM BILL FOR ENGLAND SECOND READING SECOND DAY", "date": "1831-10-04", "year": 1831, "token": 28872, "count": 298}, {"name": "nan", "date": "1806-03-03", "year": 1806, "token": 38186, "count": 291}, {"name": "THE TREATY OF PEACE  ADJOURNED DEBATE SECOND NIGHT", "date": "1856-05-06", "year": 1856, "token": 49128, "count": 288}, {"name": "REFORM OF PARLIAMENT", "date": "1821-04-17", "year": 1821, "token": 32016, "count": 284}, {"name": "AUSTRALIAN COLONIES BILL", "date": "1849-06-04", "year": 1849, "token": 5457, "count": 282}, {"name": "NEW FOUNDLAND", "date": "1842-08-03", "year": 1842, "token": 8895, "count": 282}, {"name": "ADDRESS IN ANSWER TO THE SPEECH", "date": "1852-02-03", "year": 1852, "token": 62026, "count": 279}, {"name": "RESOLUTION ADJOURNED DEBATE SECOND NIGHT", "date": "1882-03-20", "year": 1882, "token": 38263, "count": 278}, {"name": "NEW ZEALAND GOVERNMENT BILL", "date": "1852-06-22", "year": 1852, "token": 18451, "count": 277}, {"name": "PORTUGAL", "date": "1847-06-11", "year": 1847, "token": 33469, "count": 273}, {"name": "SUPPLY EXPENSES OF KAFFIR WAR", "date": "1851-06-13", "year": 1851, "token": 12841, "count": 269}, {"name": "COMMISSION OF INQUIRY", "date": "1822-07-25", "year": 1822, "token": 16705, "count": 268}, {"name": "HEREDITARY LEGISLATORS", "date": "1890-03-21", "year": 1890, "token": 10905, "count": 267}, {"name": "VICTORIA GOVERNMENT BILL", "date": "1855-06-14", "year": 1855, "token": 13876, "count": 266}, {"name": "PARLIAMENTARY REFORM BILL FOR ENGLAND THIRD READING ADJOURNED DEBATE", "date": "1832-03-20", "year": 1832, "token": 32720, "count": 263}, {"name": "POLAND", "date": "1832-06-28", "year": 1832, "token": 14909, "count": 261}, {"name": "ADJOURNED DEBATE SEVENTH SIGHT", "date": "1866-04-26", "year": 1866, "token": 41936, "count": 258}, {"name": "AFFAIRS OF PORTUGAL", "date": "1830-03-10", "year": 1830, "token": 32310, "count": 258}, {"name": "THE CANADAS", "date": "1834-04-15", "year": 1834, "token": 20819, "count": 256}, {"name": "AUSTRALIAN COLONIES GOVERNMENT BILL", "date": "1850-08-01", "year": 1850, "token": 7520, "count": 255}, {"name": "NEW SOUTH WALES GOVERNMENT BILL", "date": "1855-06-14", "year": 1855, "token": 9571, "count": 254}, {"name": "PORTUGAL ADJOURNED DEBATE", "date": "1847-06-14", "year": 1847, "token": 28129, "count": 254}, {"name": "STATE OF IRELAND", "date": "1812-01-31", "year": 1812, "token": 27809, "count": 252}, {"name": "PAPERS MOVED FOR", "date": "1861-05-07", "year": 1861, "token": 24228, "count": 251}, {"name": "DENMARK AND GERMANY TREATY OF LONDON  RESOLUTION", "date": "1864-04-19", "year": 1864, "token": 34882, "count": 250}, {"name": "MINISTERIAL PLAN OF PARLIAMENTARY REFORM", "date": "1831-03-01", "year": 1831, "token": 30170, "count": 250}, {"name": "PARLIAMENTARY REFORM BILL FOR ENGLAND THIRD READING ADJOURNED DEBATE THIRD DAY", "date": "1832-03-22", "year": 1832, "token": 53099, "count": 249}, {"name": "ADJOURNED DEBATE ON THE ADDRESS", "date": "1895-02-18", "year": 1895, "token": 33478, "count": 248}, {"name": "AFFAIRS OF SICILY", "date": "1821-06-21", "year": 1821, "token": 7983, "count": 247}, {"name": "HOUSE OF LORDS VETO", "date": "1903-05-27", "year": 1903, "token": 7207, "count": 247}, {"name": "QUESTION OBSERVATIONS", "date": "1893-07-21", "year": 1893, "token": 6651, "count": 247}, {"name": "ADJOURNED DEBATE SECOND NIGHT", "date": "1883-02-16", "year": 1883, "token": 27820, "count": 245}, {"name": "SECOND READING", "date": "1884-11-06", "year": 1884, "token": 33168, "count": 243}, {"name": "CONDUCT OF LORD ABINGER", "date": "1843-02-21", "year": 1843, "token": 42994, "count": 240}, {"name": "NATIONAL REPRESENTATION", "date": "1850-02-28", "year": 1850, "token": 34172, "count": 240}, {"name": "ADDRESS MOVED", "date": "1858-05-04", "year": 1858, "token": 25691, "count": 239}, {"name": "PARLIAMENTARY REFORM BILL FOR ENGLAND SECOND READING THIRD DAY", "date": "1832-04-11", "year": 1832, "token": 37031, "count": 238}, {"name": "SECOND READING FIRST NIGHT", "date": "1861-05-13", "year": 1861, "token": 33339, "count": 234}, {"name": "CONVENTUAL AND MONASTIC INSTI TUTIONS", "date": "1854-03-28", "year": 1854, "token": 22411, "count": 230}, {"name": "OBSERVATIONS", "date": "1868-05-08", "year": 1868, "token": 16049, "count": 230}, {"name": "SECOND READING", "date": "1888-04-26", "year": 1888, "token": 17309, "count": 228}, {"name": "PARLIAMENTARY VOTERS IRELAND BILL", "date": "1850-07-30", "year": 1850, "token": 17266, "count": 227}, {"name": "COMMITTEE Progress th May", "date": "1893-05-11", "year": 1893, "token": 27346, "count": 226}, {"name": "COMMONWEALTH OF AUSTRALIA CONSTITUTION BILL", "date": "1950-05-14", "year": 1900, "token": 23334, "count": 226}, {"name": "AFFAIRS OF CANADA ADJOURNED DEBATE", "date": "1837-03-08", "year": 1837, "token": 27584, "count": 224}, {"name": "PAPER PRESENTED OBSERVATIONS", "date": "1859-07-28", "year": 1859, "token": 36003, "count": 224}, {"name": "RECOVERY OF PERSONAL LIBERTY BILL", "date": "1853-06-22", "year": 1853, "token": 21703, "count": 224}, {"name": "COMMITTEE FIRST NIGHT", "date": "1861-05-27", "year": 1861, "token": 33801, "count": 223}, {"name": "POLAND", "date": "1832-04-18", "year": 1832, "token": 11158, "count": 219}, {"name": "SEDITIOUS MEETINGS PREVENTION BILL", "date": "1819-12-13", "year": 1819, "token": 21595, "count": 218}, {"name": "NEW SOUTH WALES GOVERNMENT  WASTE LANDS AUSTRALIA ACTS RE PEAL BILLS", "date": "1855-05-17", "year": 1855, "token": 6965, "count": 216}, {"name": "OATHS BILL COMMITTEE", "date": "1857-06-15", "year": 1857, "token": 42862, "count": 215}, {"name": "LORDS AMENDMENTS ADJOURNED DEBATE", "date": "1871-08-15", "year": 1871, "token": 20023, "count": 214}, {"name": "POLISH HUNGARIAN AND ITALIAN REFUGEES", "date": "1850-02-07", "year": 1850, "token": 14916, "count": 214}, {"name": "THE TRANSVAAL CONSTITUTION", "date": "1906-07-30", "year": 1906, "token": 20744, "count": 213}, {"name": "TRANSPORTATION TO THE AUSTRALIAN COLONIES", "date": "1853-02-24", "year": 1853, "token": 15411, "count": 212}, {"name": "Seed1-Napie", "date": "Seed1-Napier", "year": 1884, "token": 345264, "count": 211}, {"name": "nan", "date": "1805-05-14", "year": 1805, "token": 57601, "count": 211}, {"name": "REPEAL OF THE UNION IRELAND ADJOURNED DEBATE", "date": "1834-04-24", "year": 1834, "token": 30906, "count": 210}, {"name": "SECOND READING", "date": "1871-07-31", "year": 1871, "token": 34198, "count": 210}, {"name": "PARLIAMENTARY REFORM BILL FOR ENGLAND SECOND READING", "date": "1831-12-16", "year": 1831, "token": 30179, "count": 209}, {"name": "CONTROVERTED ELECTIONS", "date": "1839-02-14", "year": 1839, "token": 22003, "count": 208}, {"name": "SECOND READING", "date": "1860-05-21", "year": 1860, "token": 45279, "count": 205}, {"name": "AFFAIRS OF POLAND", "date": "1863-07-20", "year": 1863, "token": 32953, "count": 204}, {"name": "COMMITTEE FOR PRIVILEGES THE WENSLEYDALE PEERAGE", "date": "1856-02-22", "year": 1856, "token": 26574, "count": 204}, {"name": "REFORM OF PARLIAMENT", "date": "1819-07-01", "year": 1819, "token": 25273, "count": 203}, {"name": "CONVENTUAL AND MONASTIC INSTI TUTIONS", "date": "1854-02-28", "year": 1854, "token": 34177, "count": 202}, {"name": "POLITICAL UNIONS", "date": "1833-06-27", "year": 1833, "token": 7634, "count": 202}, {"name": "SUPPLY FORCES IN THE MEDITERRANEAN VOTE OF CREDIT", "date": "1882-07-25", "year": 1882, "token": 49675, "count": 198}, {"name": "GERMANY PROTOCOL OF THE DIET", "date": "1832-08-02", "year": 1832, "token": 17455, "count": 196}, {"name": "SIR FRANCIS BURDETTS PLAN OF PARLIAMENTARY REFORM", "date": "1809-06-15", "year": 1809, "token": 12063, "count": 196}, {"name": "PRIVILEGE PRINTED PAPERS", "date": "1845-06-26", "year": 1845, "token": 39356, "count": 195}, {"name": "PORTUGAL", "date": "1847-07-05", "year": 1847, "token": 18552, "count": 194}, {"name": "RESOLUTION ADJOURNED DEBATE", "date": "1879-02-20", "year": 1879, "token": 26916, "count": 193}, {"name": "ADDRESS TO HER MAJESTY", "date": "1864-07-08", "year": 1864, "token": 48246, "count": 191}, {"name": "COMMITTEE", "date": "1858-07-19", "year": 1858, "token": 17065, "count": 191}, {"name": "IONIAN ISLANDS CONDUCT OF SIR THOMAS MAITLAND", "date": "1821-06-07", "year": 1821, "token": 8543, "count": 191}, {"name": "NEWSPAPER STAMP DUTIES BILL", "date": "1819-12-22", "year": 1819, "token": 22822, "count": 190}, {"name": "PARLIAMENTARY REFORM   BILL FOR ENGLAND SECOND HEADING  ADJOURNED DEBATE THIRD DAY", "date": "1831-07-06", "year": 1831, "token": 32549, "count": 190}, {"name": "AFFAIRS OF GREECE", "date": "1845-08-01", "year": 1845, "token": 7392, "count": 187}, {"name": "SEDITIOUS MEETINGS PREVENTION BILL", "date": "1819-11-29", "year": 1819, "token": 16104, "count": 184}, {"name": "COMMITTEE ON THE STATE OF THE LAWS AFFECTING THE ROMAN CATHOLICS", "date": "1813-03-09", "year": 1813, "token": 21791, "count": 183}, {"name": "MINISTERIAL PLAN OF PARLIAMENTARY REFORM ADJOURNED DEBATE", "date": "1831-03-08", "year": 1831, "token": 27177, "count": 182}, {"name": "CHURCH OF SCOTLAND BENEFICES BILL", "date": "1843-07-31", "year": 1843, "token": 26871, "count": 180}, {"name": "EASTINDIA COMPANYS CHARTER", "date": "1833-07-10", "year": 1833, "token": 21805, "count": 180}, {"name": "PARLIAMENTARY REFORM BILL FOR ENGLAND SECOND READING ADJOURNED DEBATE", "date": "1831-12-17", "year": 1831, "token": 49010, "count": 180}, {"name": "RUSSIAN INVASION OF HUNGARY", "date": "1849-07-21", "year": 1849, "token": 12779, "count": 180}, {"name": "CRACOW ADJOURNED DEBATE", "date": "1847-03-11", "year": 1847, "token": 27283, "count": 178}, {"name": "PARLIAMENTARY REFORM BILL FOR ENGLAND COMMITTEE FIRST DAY", "date": "1831-07-12", "year": 1831, "token": 22587, "count": 178}, {"name": "THE CANADAS", "date": "1836-05-16", "year": 1836, "token": 11605, "count": 178}, {"name": "MINISTERIAL ARRANGEMENTS EXPLANATIONS", "date": "1832-05-18", "year": 1832, "token": 11567, "count": 175}, {"name": "SECOND READING", "date": "1873-07-02", "year": 1873, "token": 13447, "count": 175}, {"name": "nan", "date": "1808-03-08", "year": 1808, "token": 26572, "count": 175}, {"name": "LEGISLATIVE COUNCIL CANADA BILL", "date": "1854-06-15", "year": 1854, "token": 7428, "count": 174}, {"name": "AFFAIRS OF CANADA", "date": "1838-02-02", "year": 1838, "token": 28499, "count": 172}, {"name": "SIR FRANCIS BURDETTS MOTION RESPECTING THE REGENCY", "date": "1813-02-23", "year": 1813, "token": 7984, "count": 172}, {"name": "SECOND READING", "date": "1879-03-25", "year": 1879, "token": 19512, "count": 171}, {"name": "GOVERNMENT OF LOWER CANADA", "date": "1839-07-26", "year": 1839, "token": 18953, "count": 170}, {"name": "INSPECTION OF NUNNERIES", "date": "1853-05-10", "year": 1853, "token": 22795, "count": 170}, {"name": "JAMAICA SUSPENSION OF THE CONSTITUTION", "date": "1839-04-09", "year": 1839, "token": 24306, "count": 170}, {"name": "SUPPRESSION OF DISTURBANCES IRELAND ADJOURNED DEBATE", "date": "1833-03-04", "year": 1833, "token": 30817, "count": 170}, {"name": "LEAVE", "date": "1857-07-21", "year": 1857, "token": 24984, "count": 169}, {"name": "COMMITTEE FIFTH RESOLUTION", "date": "1858-06-14", "year": 1858, "token": 26598, "count": 168}, {"name": "NEW ZEALAND GOVERNMENT BILL", "date": "1848-02-29", "year": 1848, "token": 7866, "count": 168}, {"name": "RESOLUTION", "date": "1893-08-04", "year": 1893, "token": 5913, "count": 166}, {"name": "OXFORD UNIVERSITY BILL", "date": "1854-05-01", "year": 1854, "token": 22579, "count": 165}, {"name": "ADJOURNED DEBATE THIRD NIGHT", "date": "1887-04-12", "year": 1887, "token": 39984, "count": 164}, {"name": "CONTROVERTED ELECTIONS", "date": "1838-04-02", "year": 1838, "token": 26905, "count": 164}, {"name": "COMMITTEE MOVED FOR", "date": "1858-04-26", "year": 1858, "token": 26242, "count": 163}, {"name": "PARLIAMENTAYR REFORM BILL  SECOND READING  ADJOURNED DEBATE", "date": "1831-03-22", "year": 1831, "token": 34674, "count": 162}, {"name": "THIRD RESOLUTION ADJOURNED DEBATE", "date": "1858-06-07", "year": 1858, "token": 31670, "count": 162}, {"name": "MOTION FOR A SELECT COMMITTEE", "date": "1878-06-18", "year": 1878, "token": 20243, "count": 161}, {"name": "NEW ZEALAND GOVERNMENT BILL", "date": "1848-02-09", "year": 1848, "token": 15881, "count": 161}, {"name": "LATE EX OFFICIO PROSECUTIONS", "date": "1830-03-02", "year": 1830, "token": 28974, "count": 160}, {"name": "MOTION FOR LEAVE DEBATE RESUMED", "date": "1858-02-09", "year": 1858, "token": 41109, "count": 160}, {"name": "IRISH TITHES", "date": "1809-05-19", "year": 1809, "token": 17744, "count": 159}, {"name": "NEW ZEALAND   ADJOURNED DEBATE", "date": "1845-07-23", "year": 1845, "token": 21710, "count": 159}, {"name": "RESOLUTION", "date": "1870-03-14", "year": 1870, "token": 16801, "count": 159}, {"name": "ROMAN CATHOLIC QUESTION", "date": "1817-05-09", "year": 1817, "token": 52725, "count": 159}, {"name": "nan", "date": "1827-06-08", "year": 1827, "token": 14031, "count": 159}, {"name": "AFFAIRS OF GREECE", "date": "1848-03-02", "year": 1848, "token": 4907, "count": 158}, {"name": "CRETE", "date": "1897-04-12", "year": 1897, "token": 28940, "count": 158}, {"name": "PARLIAMENTARY REFORM", "date": "1830-05-28", "year": 1830, "token": 20409, "count": 158}, {"name": "ADJOURNED DEBATE THIRD NIGHT", "date": "1858-02-18", "year": 1858, "token": 39101, "count": 155}, {"name": "MOTION RESPECTING SIR ROBERT WILSONS REMOVAL FROM THE ARMY", "date": "1822-02-13", "year": 1822, "token": 24929, "count": 155}, {"name": "OBSERVATIONS", "date": "1876-03-14", "year": 1876, "token": 24704, "count": 155}, {"name": "ADJOURNED DEBATE", "date": "1895-02-15", "year": 1895, "token": 32460, "count": 154}, {"name": "GOVERNMENT OF JAMAICA SECOND MEASURE", "date": "1839-07-02", "year": 1839, "token": 23255, "count": 154}, {"name": "MINISTERIAL PLAN OF PARLIAMENTARY REFORM ADJOURNED DEBATE THIRD DAY", "date": "1831-03-03", "year": 1831, "token": 33331, "count": 153}, {"name": "NEGOTIATIONS RELATIVE TO SPAIN", "date": "1823-04-28", "year": 1823, "token": 25808, "count": 153}, {"name": "SEDITIOUS MEETINGS BILL", "date": "1817-03-25", "year": 1817, "token": 17493, "count": 153}, {"name": "NEWSPAPER STAMP DUTIES BILL", "date": "1819-12-21", "year": 1819, "token": 1991, "count": 152}, {"name": "INDIAN TARIFF ACT ", "date": "1899-06-15", "year": 1899, "token": 45252, "count": 151}, {"name": "SERVIA AND RUSSIA", "date": "1843-05-05", "year": 1843, "token": 10478, "count": 151}, {"name": "EXOFFICIO INFORMATIONS IN IRELAND", "date": "1823-04-15", "year": 1823, "token": 20234, "count": 150}, {"name": "SUPPRESSION OF DISTURBANCES IRELAND ADJOURNED DEBATE", "date": "1833-03-01", "year": 1833, "token": 30086, "count": 150}, {"name": "RESOLUTION", "date": "1887-06-10", "year": 1887, "token": 29565, "count": 149}, {"name": "TURKISH LOAN BILL", "date": "1855-07-27", "year": 1855, "token": 23706, "count": 149}, {"name": "nan", "date": "1807-02-13", "year": 1807, "token": 16696, "count": 149}, {"name": "ELECTIVE FRANCHISE PARLIAMENT ARY REFORM", "date": "1852-03-25", "year": 1852, "token": 34620, "count": 148}, {"name": "POLAND", "date": "1842-06-30", "year": 1842, "token": 12190, "count": 148}, {"name": "BUSINESS OF THE HOUSE SUPPLY ETC", "date": "1905-03-15", "year": 1905, "token": 20880, "count": 147}, {"name": "THE SUPPLIES CONDUCT OF THE PEERS", "date": "1835-08-21", "year": 1835, "token": 5231, "count": 147}, {"name": "NAPLES CONDUCT OF THE ALLIED POWERS", "date": "1821-02-19", "year": 1821, "token": 20840, "count": 146}, {"name": "PARLIAMENT BUSINESS OF THE HOUSE THE NEW RULES OF PROCEDURE THE FIRST RESOLUTION PUTTING THE QUESTION", "date": "1882-02-20", "year": 1882, "token": 28127, "count": 146}, {"name": "PORTUGAL", "date": "1847-06-15", "year": 1847, "token": 23656, "count": 146}, {"name": "STATEMENT OF THE DELEGATE FROM EDINBURGH DISTRICT", "date": "1842-05-03", "year": 1842, "token": 25866, "count": 146}, {"name": "THE BALLOT", "date": "1848-08-08", "year": 1848, "token": 18739, "count": 145}, {"name": "MUNICIPAL CORPORATIONS IRELAND LORDS AMENDMENTS ADJOURNED DEBATE", "date": "1836-06-10", "year": 1836, "token": 38110, "count": 144}, {"name": "PARLIAMENTARY REFORM BILL FOR ENGLAND SECOND READING  FIRST DAY", "date": "1831-10-03", "year": 1831, "token": 22822, "count": 144}, {"name": "PARLIAMENTARY REFORMBILL FOR ENGLAND ADJOURNED DEBATE", "date": "1831-07-05", "year": 1831, "token": 25299, "count": 144}, {"name": "ADDRESS ON THE KINGS SPEECH AT THE OPENING OF THE SESSION", "date": "1824-02-03", "year": 1824, "token": 16365, "count": 143}, {"name": "CANADA", "date": "1837-05-09", "year": 1837, "token": 16724, "count": 143}, {"name": "NEGOTIATIONS RELATIVE TO SPAIN", "date": "1823-04-29", "year": 1823, "token": 29379, "count": 143}, {"name": "ADJOURNED DEBATE THIRD NIGHT", "date": "1878-05-23", "year": 1878, "token": 44006, "count": 142}, {"name": "REFORM OF PARLIAMENT", "date": "1826-04-27", "year": 1826, "token": 22459, "count": 142}, {"name": "RESOLUTIONS", "date": "1864-04-11", "year": 1864, "token": 26884, "count": 142}, {"name": "HABEAS CORPUS SUSPENSION BILL", "date": "1817-06-27", "year": 1817, "token": 18673, "count": 141}, {"name": "STATE OF SLAVERY IN THE COLONIES", "date": "1826-05-19", "year": 1826, "token": 32968, "count": 141}, {"name": "THE KINGS SPEECH ON OPENING THE SESSION", "date": "1824-02-03", "year": 1824, "token": 16525, "count": 141}, {"name": "CHURCH OF SCOTLAND ADJOURNED DEBATE", "date": "1843-03-08", "year": 1843, "token": 28527, "count": 139}, {"name": "REPEAL OF THE UNION IRELAND", "date": "1834-04-22", "year": 1834, "token": 26377, "count": 139}, {"name": "SALE OF FOOD AND DRUGS BILL", "date": "1899-07-17", "year": 1899, "token": 25970, "count": 138}, {"name": "APPELLATE JURISDICTION HOUSE OF LORDS BILL", "date": "1856-07-10", "year": 1856, "token": 18773, "count": 137}, {"name": "PARLIAMENTARY REFORM REPRESENTATION OF THE PEOPLE", "date": "1867-02-11", "year": 1867, "token": 14281, "count": 137}, {"name": "FOREIGN AFFAIRS CONSTITUTION OF SPAIN", "date": "1852-05-21", "year": 1852, "token": 4072, "count": 136}, {"name": "PARLIAMENTARY REFORM BILL FOR ENGLAND SECOND READING FOURTH DAY", "date": "1832-04-13", "year": 1832, "token": 52377, "count": 136}, {"name": "REFORM OF PARLIAMENT", "date": "1823-04-24", "year": 1823, "token": 11050, "count": 136}, {"name": "SECOND READING", "date": "1872-02-15", "year": 1872, "token": 18460, "count": 136}, {"name": "COLONIAL BISHOPS BILL ADJOURNED DEBATE", "date": "1852-05-19", "year": 1852, "token": 20618, "count": 135}, {"name": "COMMITTEE", "date": "1877-07-24", "year": 1877, "token": 18927, "count": 135}, {"name": "REFORM BILL FOR IRELAND", "date": "1831-03-24", "year": 1831, "token": 21586, "count": 134}, {"name": "RECOGNITION OF THE INDEPENDENCE OF SOUTH AMERICA", "date": "1824-03-15", "year": 1824, "token": 15516, "count": 133}, {"name": "ADJOURNED DEBATE SECOND NIGHT", "date": "1886-01-22", "year": 1886, "token": 26886, "count": 132}, {"name": "COMMITTEE Progress nd April", "date": "1869-04-23", "year": 1869, "token": 21865, "count": 132}, {"name": "NO  COMMITTEE", "date": "1869-06-03", "year": 1869, "token": 12728, "count": 132}, {"name": "SECOND READING ADJOURNED DEBATE SECOND NIGHT", "date": "1874-07-13", "year": 1874, "token": 29190, "count": 132}, {"name": "CRACOW", "date": "1847-03-16", "year": 1847, "token": 32304, "count": 131}, {"name": "JEWISH DISABILITIES BILL", "date": "1848-04-03", "year": 1848, "token": 13852, "count": 131}, {"name": "THE BALLOT LEAVE", "date": "1857-06-30", "year": 1857, "token": 20576, "count": 131}, {"name": "THE SOUTH AFRICAN CONSTITUTIONS", "date": "1906-12-17", "year": 1906, "token": 12827, "count": 130}, {"name": "BILL  SECOND READING", "date": "1865-05-03", "year": 1865, "token": 32997, "count": 129}, {"name": "EVACUATION OF SPAIN BY THE FRENCH ARMY", "date": "1824-03-18", "year": 1824, "token": 20905, "count": 129}, {"name": "POUTUGAL", "date": "1830-02-18", "year": 1830, "token": 21116, "count": 129}, {"name": "PROPERTY DISPOSAL BILL", "date": "1854-03-14", "year": 1854, "token": 9132, "count": 129}, {"name": "CLASS V FOREIGN AND COLONIAL SERVICES", "date": "1881-08-06", "year": 1881, "token": 8775, "count": 128}, {"name": "CRACOW", "date": "1847-03-04", "year": 1847, "token": 14858, "count": 128}, {"name": "NATIONAL REPRESENTATION", "date": "1849-06-05", "year": 1849, "token": 31808, "count": 128}, {"name": "OBSERVATIONS", "date": "1867-02-22", "year": 1867, "token": 24004, "count": 128}, {"name": "THE HOUSE OF LORDS AND THE REGISTRATION OF VOTERS IRELAND BILL", "date": "1880-09-03", "year": 1880, "token": 21837, "count": 128}, {"name": "ADJOURNMENT OF PARLIAMENT", "date": "1813-12-20", "year": 1813, "token": 14492, "count": 127}, {"name": "IONIAN ISLANDS", "date": "1840-06-23", "year": 1840, "token": 2469, "count": 127}, {"name": "COMMITTEE", "date": "1890-06-26", "year": 1890, "token": 9597, "count": 126}, {"name": "QUESTION", "date": "1863-05-15", "year": 1863, "token": 12637, "count": 126}, {"name": "SECOND READING", "date": "1877-02-15", "year": 1877, "token": 25388, "count": 126}, {"name": "SUPPRESSION OF DISTUUBANCES IRELAND", "date": "1833-02-27", "year": 1833, "token": 23556, "count": 126}, {"name": "WEST INDIES JAMAICA SEIZURE OF THE FLORENCE OBSERVATIONS", "date": "1883-03-09", "year": 1883, "token": 10703, "count": 126}, {"name": "ANSWER TO THE THIRD QUESTION", "date": "1812-04-21", "year": 1812, "token": 41940, "count": 125}, {"name": "CLASS II", "date": "1907-06-20", "year": 1907, "token": 12546, "count": 125}, {"name": "MOTION FOR A SELECT COMMITTEE", "date": "1870-05-03", "year": 1870, "token": 26255, "count": 125}, {"name": "SEDITIOUS MEETINGS PREVENTION BILL", "date": "1819-12-02", "year": 1819, "token": 33930, "count": 125}, {"name": "ADDRESS ON THE PRINCE REGENTS SPEECH AT THE OPENING OF THE SESSION", "date": "1817-01-29", "year": 1817, "token": 32852, "count": 124}, {"name": "AFFAIRS OF CANADA", "date": "1838-01-29", "year": 1838, "token": 10598, "count": 124}, {"name": "BILL  SECOND READING", "date": "1872-03-20", "year": 1872, "token": 19326, "count": 124}, {"name": "CORPORATION REFORM COMMITTEE", "date": "1835-08-17", "year": 1835, "token": 9222, "count": 124}, {"name": "NEWFOUNDLAND", "date": "1841-03-30", "year": 1841, "token": 6325, "count": 124}, {"name": "SUPPLY FORCES IN THE MEDITERRANEAN VOTE OF CREDIT", "date": "1882-07-26", "year": 1882, "token": 28783, "count": 124}, {"name": "SUPPLY NEW ZEALAND", "date": "1854-06-26", "year": 1854, "token": 5869, "count": 124}, {"name": "TITHE MEETING AT NOBBER", "date": "1832-07-20", "year": 1832, "token": 6621, "count": 124}, {"name": "AFFAIRS OF CANADA", "date": "1838-02-05", "year": 1838, "token": 15236, "count": 123}, {"name": "DISESTABLISHMENT AND DISENDOWMENT OF THE CHURCH OF SCOTLAND", "date": "1890-05-02", "year": 1890, "token": 21721, "count": 123}, {"name": "ROMAN CATHOLIC CLAIMS", "date": "1821-02-28", "year": 1821, "token": 28204, "count": 123}, {"name": "NEGOTIATIONS RELATIVE TO SPAIN", "date": "1823-04-14", "year": 1823, "token": 26008, "count": 122}, {"name": "NEWFOUNDLAND", "date": "1842-06-30", "year": 1842, "token": 6757, "count": 122}, {"name": "OBSERVATIONS", "date": "1876-05-05", "year": 1876, "token": 11886, "count": 122}, {"name": "REPRESENTATION OF THE PEOPLE BILL SECOND READING", "date": "1860-03-19", "year": 1860, "token": 32133, "count": 122}, {"name": "THE LORDS COMMISSIONERS SPEECH", "date": "1812-01-07", "year": 1812, "token": 16971, "count": 122}, {"name": "PAPAL AGGRESSION ECCLESIASTICAL TITLES", "date": "1851-02-07", "year": 1851, "token": 32889, "count": 121}, {"name": "SECOND READING", "date": "1873-03-03", "year": 1873, "token": 35271, "count": 121}, {"name": "CIVIL GOVERNMENT OF THE CANADAS", "date": "1828-05-02", "year": 1828, "token": 17701, "count": 120}, {"name": "LAND LAW IRELAND BILL BILL ", "date": "1881-05-27", "year": 1881, "token": 23485, "count": 119}, {"name": "PRIVILEGE STOCKDALE v HANSARD THE SHERIFFS", "date": "1840-02-03", "year": 1840, "token": 21210, "count": 119}, {"name": "SECOND READING", "date": "1861-04-10", "year": 1861, "token": 24301, "count": 118}, {"name": "SECOND READING ADJOURNED DEBATE", "date": "1886-05-28", "year": 1886, "token": 24913, "count": 118}, {"name": "SUPPLY KAFIR WAR", "date": "1852-04-05", "year": 1852, "token": 14251, "count": 118}, {"name": "THE ADDRESS IN ANSWER TO THE QUEENS SPEECH", "date": "1844-02-01", "year": 1844, "token": 38897, "count": 118}, {"name": "AFFAIRS OF CANADA", "date": "1838-01-26", "year": 1838, "token": 21966, "count": 117}, {"name": "COMMITTEE", "date": "1869-04-16", "year": 1869, "token": 26219, "count": 117}, {"name": "CORPORATION REFORM", "date": "1835-07-20", "year": 1835, "token": 15858, "count": 117}, {"name": "MOTION FOR PAPERS", "date": "1860-02-14", "year": 1860, "token": 13841, "count": 117}, {"name": "REPEAL OF THE UNION ADJOURNED DEBATE", "date": "1834-04-23", "year": 1834, "token": 25373, "count": 117}, {"name": "ADDRESS IN ANSWER TO HER MAJESTYS MOST GRACIOUS SPEECH", "date": "1889-03-05", "year": 1889, "token": 25373, "count": 116}, {"name": "BOMBAY JUDICATURE", "date": "1830-03-08", "year": 1830, "token": 8970, "count": 116}, {"name": "CRACOW", "date": "1840-07-13", "year": 1840, "token": 10252, "count": 116}, {"name": "QUESTIONS GOVERNMENT STATEMENT", "date": "1871-07-20", "year": 1871, "token": 12784, "count": 116}, {"name": "RESOLUTION", "date": "1873-02-14", "year": 1873, "token": 16476, "count": 116}, {"name": "STATE OF GREECE", "date": "1847-04-27", "year": 1847, "token": 4347, "count": 116}, {"name": "THE BALLOT", "date": "1835-06-02", "year": 1835, "token": 42250, "count": 116}, {"name": "BLASPHEMOUS LIBEL BILL", "date": "1819-12-23", "year": 1819, "token": 21638, "count": 115}, {"name": "FURTHER CORRESPONDENCE MOVED FOR", "date": "1863-03-16", "year": 1863, "token": 29857, "count": 115}], "word": [["constitut", 14915], ["power", 5295], ["chamber", 4606], ["peopl", 3941], ["hous", 3026], ["assembl", 2444], ["form", 2337], ["institut", 2124], ["liberti", 2035], ["free", 2014], ["substitute_word", 1599], ["exercis", 1597], ["repres", 1566], ["independ", 1493], ["bodi", 1459], ["state", 1422], ["legisl", 1413], ["exist", 1362], ["freedom", 1240], ["establish", 1231], ["elect", 1212], ["crown", 1151], ["principl", 1095], ["popular", 1047], ["themselv", 984], ["privileg", 954], ["author", 951], ["nomin", 905], ["singl", 897], ["legislatur", 877], ["influenc", 780], ["control", 761], ["time", 736], ["execut", 708], ["despot", 672], ["enjoy", 668], ["function", 664], ["act", 663], ["everi", 635], ["secur", 627], ["possess", 627], ["danger", 621], ["discuss", 585], ["check", 576], ["becaus", 569], ["compos", 551], ["arbitrari", 548], ["senat", 548], ["found", 538], ["consid", 528], ["absolut", 498], ["frame", 498], ["appoint", 495], ["mere", 486], ["parliament", 481], ["period", 476], ["befor", 473], ["long", 469], ["accord", 466], ["depriv", 456], ["proceed", 455], ["year", 452], ["call", 449], ["minist", 442], ["nomine", 439], ["order", 438], ["histori", 436], ["interfer", 430], ["therefor", 429], ["destroy", 428], ["revolut", 415], ["land", 414], ["ancient", 414], ["declar", 407], ["place", 405], ["contrari", 402], ["part", 401], ["resist", 387], ["attempt", 380], ["determin", 379], ["onli", 376], ["thing", 375], ["conduct", 369], ["becom", 365], ["deliber", 362], ["creat", 356], ["suprem", 355], ["extrem", 351], ["decid", 344], ["consist", 343], ["manner", 341], ["democrat", 341], ["protect", 340], ["submit", 339], ["doubl", 338], ["unconstitut", 336], ["council", 336], ["suppos", 335], ["veto", 331], ["hand", 326], ["high", 322], ["charter", 321], ["follow", 312], ["preserv", 309], ["abolish", 298], ["upper", 298], ["essenti", 290], ["separ", 290], ["gave", 288], ["instanc", 275], ["contend", 275], ["perman", 268], ["regul", 267], ["similar", 267], ["consent", 263], ["dure", 258], ["moment", 249], ["decis", 245], ["spirit", 243], ["deni", 243], ["hereditari", 242], ["prefer", 242], ["branch", 240], ["affair", 239], ["reject", 237], ["delay", 235], ["togeth", 232], ["great", 228], ["qualif", 217], ["model", 217], ["resolut", 214], ["fundament", 212], ["theori", 208], ["clear", 206], ["encroach", 206], ["assum", 204], ["forc", 203], ["whilst", 203], ["confer", 202], ["natur", 201], ["innov", 200], ["obtain", 197], ["assert", 197], ["onc", 196], ["construct", 191], ["struggl", 191], ["depend", 191], ["futur", 189], ["properti", 189], ["tyranni", 186], ["impos", 186], ["continu", 185], ["complet", 183], ["abus", 182], ["sinc", 181], ["laid", 181], ["hear", 180], ["violat", 178], ["chosen", 177], ["irrespons", 177], ["invest", 176], ["basi", 173], ["pass", 173], ["subsequ", 172], ["necessari", 171], ["ceas", 170], ["consequ", 167], ["ani", 167], ["instrument", 166], ["ordin", 163], ["prevail", 163], ["centuri", 163], ["jealousi", 163], ["sovereign", 162], ["deputi", 162], ["utter", 161], ["usurp", 161], ["remain", 160], ["pleas", 160], ["democraci", 158], ["wast", 157], ["purpos", 157], ["settl", 157], ["true", 156], ["earli", 156], ["resolv", 156], ["guard", 155], ["bound", 155], ["worst", 154], ["becam", 154], ["summon", 154], ["republ", 154], ["modern", 152], ["erect", 151], ["restor", 150], ["tendenc", 150], ["adopt", 149], ["chose", 149], ["vest", 149], ["dictat", 145], ["confirm", 145], ["violent", 143], ["disput", 143], ["balanc", 140], ["limit", 140], ["press", 139], ["pretenc", 139], ["welfar", 138], ["harmoni", 137], ["previous", 137], ["interf", 137], ["date", 135], ["monarchi", 135], ["conceiv", 134], ["collis", 133], ["voic", 133], ["prerog", 131], ["tyrann", 131], ["grievanc", 131], ["promulg", 131], ["suspend", 130], ["longer", 130], ["wholli", 129], ["languag", 129], ["assign", 128], ["acknowledg", 127], ["distinct", 126], ["choos", 126], ["safeguard", 124], ["altern", 123], ["age", 123], ["condemn", 123], ["compel", 122], ["dissolv", 122], ["domin", 121], ["perpetu", 121], ["aristocraci", 121], ["complaint", 120], ["exclus", 120], ["monarch", 120], ["confus", 119], ["simpl", 118], ["oppress", 116], ["whatev", 116], ["ministeri", 116], ["crisi", 116], ["back", 116], ["sanction", 115], ["recognis", 115], ["uncontrol", 111], ["peculiar", 111], ["decre", 111], ["hasti", 111], ["perfect", 111], ["command", 111], ["general", 110], ["extraordinari", 109], ["suffici", 109], ["redress", 109], ["analog", 108], ["militari", 108], ["indign", 106], ["varianc", 106], ["maintain", 106], ["contest", 106], ["invad", 105], ["rule", 101], ["error", 101], ["suffrag", 101], ["tribun", 101], ["mischiev", 101], ["wisdom", 100], ["mix", 99], ["absurd", 99], ["discont", 99], ["requisit", 98], ["till", 97], ["obedi", 96], ["republican", 96], ["destruct", 95], ["congress", 94], ["usag", 94], ["estat", 94], ["mockeri", 93], ["restrain", 93], ["jealous", 91], ["distant", 91], ["imit", 91], ["theoret", 90], ["howev", 90], ["unlimit", 89], ["impeach", 89], ["interpos", 89], ["subvert", 89], ["delib", 88], ["guarante", 87], ["infring", 87], ["copi", 86], ["elector", 86], ["reviv", 85], ["conclud", 84], ["doctrin", 84], ["end", 83], ["strongest", 83], ["servant", 82], ["vital", 82], ["court", 82], ["abov", 82], ["fatal", 81], ["misl", 81], ["star", 81], ["show", 80], ["unwil", 80], ["endeavour", 79], ["destini", 79], ["choic", 79], ["ground", 79], ["conform", 78], ["prove", 78], ["capac", 78], ["essenc", 77], ["oligarchi", 77], ["tyrant", 77], ["maxim", 77], ["justifi", 76], ["reason", 76], ["characterist", 75], ["abrog", 74], ["reign", 74], ["trampl", 74], ["abil", 73], ["record", 73], ["pleasur", 73], ["digniti", 71], ["inher", 70], ["restraint", 70], ["subvers", 70], ["capric", 69], ["persist", 68], ["uniform", 68], ["protector", 68], ["withhold", 67], ["contempt", 67], ["incompat", 66], ["enact", 66], ["substanc", 66], ["valid", 65], ["law", 65], ["collect", 64], ["durat", 64], ["wield", 63], ["defin", 62], ["unfit", 62], ["acquiesc", 61], ["factious", 61], ["seri", 61], ["draw", 60], ["thwart", 60], ["tool", 60], ["interposit", 59], ["quot", 58], ["knight", 58], ["predomin", 57], ["curtail", 57], ["citizen", 57], ["realm", 57], ["histor", 56], ["pray", 56], ["account", 56], ["entitl", 56], ["resort", 55], ["asid", 55], ["total", 55], ["afterward", 55], ["male", 55], ["newli", 55], ["complianc", 55], ["lesson", 54], ["discord", 54], ["sentiment", 54], ["banish", 53], ["annex", 52], ["referendum", 52], ["fetter", 52], ["hint", 51], ["revolutionari", 51], ["subservi", 51], ["darl", 50], ["solv", 50], ["nought", 50], ["obnoxi", 50], ["incorpor", 50], ["corrupt", 49], ["earliest", 49], ["overpow", 49], ["ambiti", 49], ["aristocrat", 48], ["violenc", 48], ["civil", 48], ["left", 48], ["surrend", 48], ["functionari", 48], ["unrestrain", 48], ["discret", 47], ["sixth", 47], ["commonwealth", 46], ["twelv", 46], ["mutil", 46], ["menac", 46], ["stretch", 45], ["ripe", 45], ["ancestor", 45], ["outlin", 45], ["autocrat", 44], ["persuad", 43], ["subsist", 43], ["intern", 42], ["give", 42], ["ensur", 42], ["submiss", 41], ["dare", 41], ["conced", 41], ["offspr", 41], ["contriv", 40], ["annihil", 40], ["impuls", 40], ["precipit", 40], ["servil", 40], ["abridg", 39], ["solitari", 39], ["tenur", 39], ["assumpt", 39], ["gradual", 39], ["passiv", 39], ["inviol", 38], ["unfett", 37], ["abdic", 37], ["pale", 37], ["annul", 37], ["predilect", 36], ["arrog", 36], ["threaten", 36], ["genius", 35], ["departur", 35], ["medium", 35], ["eighteen", 34], ["mighti", 34], ["flagrant", 34], ["string", 34], ["founder", 33], ["custom", 33], ["irrevoc", 33], ["monopoli", 32], ["demonstr", 32], ["machin", 32], ["unjustifi", 31], ["conjoint", 31], ["congeni", 31], ["yoke", 30], ["actual", 30], ["concess", 30], ["declaratori", 30], ["notwithstand", 30], ["happili", 29], ["undisturb", 29], ["solicit", 29], ["excit", 29], ["passion", 29], ["sacr", 28], ["mob", 28], ["sway", 28], ["anarchi", 28], ["aggrav", 28], ["unsuccess", 28], ["transit", 28], ["design", 28], ["fifti", 27], ["palat", 27], ["distast", 27], ["writer", 27], ["overaw", 27], ["exposit", 27], ["birthright", 27], ["irreconcil", 26], ["negat", 26], ["convok", 25], ["inconsist", 25], ["likewis", 25], ["occup", 25], ["lover", 25], ["dictatorship", 25], ["forthwith", 25], ["sphere", 25], ["wholesom", 24], ["memor", 24], ["defianc", 24], ["null", 24], ["depositari", 24], ["mandat", 23], ["faction", 23], ["vexati", 23], ["cherish", 23], ["powerless", 23], ["arbitrarili", 23], ["thereof", 23], ["radic", 22], ["noblest", 22], ["extern", 22], ["hot", 22], ["censorship", 21], ["omnipot", 21], ["transplant", 21], ["fox", 21], ["disposit", 21], ["sundri", 21], ["tumult", 21], ["unprejud", 21], ["inim", 21], ["unwarrant", 20], ["blow", 20], ["succumb", 20], ["due", 20], ["caprici", 19], ["freed", 19], ["coup", 19], ["overrid", 19], ["guardian", 19], ["realiti", 19], ["feder", 19], ["appendag", 19], ["accredit", 19], ["key", 18], ["cite", 18], ["transcend", 18], ["brightest", 18], ["dubious", 17], ["turnpik", 17], ["audaci", 17], ["regent", 17], ["neutralis", 17], ["enslav", 17], ["rivet", 17], ["demarc", 17], ["sympathis", 17], ["unrestrict", 17], ["tame", 16], ["graft", 16], ["miniatur", 16], ["trial", 16], ["began", 16], ["corpor", 16], ["verbatim", 16], ["forefath", 15], ["tile", 15], ["sire", 15], ["unheard", 15], ["mock", 15], ["bearer", 14], ["iota", 14], ["upheld", 14], ["haven", 14], ["strictur", 14], ["abbot", 14], ["governor", 13], ["squander", 13], ["phantom", 13], ["stab", 13], ["feebl", 13], ["licenc", 12], ["bold", 12], ["befit", 12], ["newfangl", 12], ["bias", 12], ["crude", 12], ["seventeenth", 12], ["actor", 12], ["dispossess", 12], ["monast", 12], ["asylum", 11], ["appanag", 11], ["feign", 11], ["compon", 11], ["forecast", 11], ["revolutionis", 11], ["spoliat", 11], ["quorum", 11], ["unspecifi", 11], ["code", 11], ["amount", 11], ["nelson", 11], ["alarmist", 11], ["undoubt", 10], ["hack", 10], ["sapient", 10], ["unmak", 10], ["breez", 10], ["anywher", 10], ["desper", 10], ["madam", 10], ["absente", 10], ["quinquenni", 9], ["bas", 9], ["sensit", 9], ["unusu", 9], ["inscrib", 9], ["unison", 9], ["momentari", 9], ["warlik", 9], ["reassert", 9], ["discover", 9], ["jay", 8], ["bless", 8], ["piebald", 8], ["inalien", 8], ["autocraci", 8], ["relinquish", 8], ["rear", 8], ["strangest", 8], ["freeborn", 8], ["stalwart", 8], ["constitution", 8], ["entri", 8], ["enviabl", 8], ["tyrannis", 7], ["curdl", 7], ["insuffer", 7], ["temporari", 7], ["safeti", 7], ["benumb", 7], ["presuppos", 7], ["unsatisfi", 7], ["behead", 7], ["lacon", 6], ["trespass", 6], ["signet", 6], ["gaoler", 6], ["ceremoni", 6], ["guis", 6], ["reverber", 6], ["croak", 6], ["conglomer", 5], ["approb", 5], ["bureaux", 5], ["federalist", 5], ["untrammel", 5], ["herd", 5], ["secess", 5], ["derid", 5], ["absent", 5], ["bicamer", 5], ["corps", 5], ["whim", 4], ["inquisit", 4], ["euthanasia", 4], ["unapprov", 4], ["parapet", 4], ["outpour", 4], ["indec", 4], ["unwelcom", 4], ["grin", 4], ["obeis", 4], ["abrupt", 3], ["embarrass", 3], ["pliant", 3], ["calv", 3], ["intermix", 3], ["singleton", 3], ["rehears", 3], ["addl", 3], ["wintri", 3], ["den", 3], ["munch", 3], ["striven", 3], ["tiff", 3], ["strata", 3], ["impract", 3], ["mismanag", 3], ["ref", 3], ["compli", 3], ["downward", 2], ["furtiv", 2], ["sedit", 2], ["headlong", 2], ["outbid", 2], ["waft", 2], ["exception", 2], ["purgat", 2], ["analysi", 2], ["silliest", 2], ["corpora", 2], ["centaur", 2], ["elev", 2], ["built", 2], ["tabl", 2], ["unravel", 2], ["bulkier", 2], ["tack", 2], ["impecc", 2], ["revisionari", 2], ["pedal", 2], ["sapless", 2], ["porcupin", 2], ["moreov", 2], ["gabbl", 2], ["cub", 2], ["prison", 2], ["crag", 2], ["eyeless", 2], ["fisticuff", 2], ["pettiest", 2], ["doubt", 2], ["tardili", 1], ["dire", 1], ["clarendons", 1], ["enfold", 1], ["armouri", 1], ["elast", 1], ["hereinaft", 1], ["drawback", 1], ["tenanc", 1], ["cedilla", 1], ["dye", 1], ["typograph", 1], ["chuckl", 1], ["outpati", 1], ["skrvices", 1], ["overlook", 1], ["inconceiv", 1], ["nerveless", 1], ["bombast", 1], ["uner", 1], ["druid", 1], ["friction", 1], ["equiti", 1], ["flotilla", 1], ["change", 1], ["cutan", 1], ["substanti", 1], ["triplex", 1], ["pernici", 1], ["freest", 1], ["yeasti", 1], ["throb", 1], ["sect", 1], ["lawyer", 1], ["luck", 1], ["leaden", 1], ["duet", 1], ["bra", 1], ["retro", 1], ["umbrella", 1], ["heedless", 1], ["haddock", 1], ["ski", 1], ["musketri", 1], ["base", 1], ["archivist", 1], ["fusti", 1], ["unachiev", 1], ["rooster", 1], ["salesman", 1], ["prototyp", 1], ["content", 1], ["incarnadin", 1], ["alli", 1], ["gimlet", 1], ["praemunire", 1], ["alm", 1], ["thereto", 1], ["archeri", 1], ["danc", 1], ["thelwall", 1], ["constitutions", 1], ["lieg", 1]], "year": [6, 195, 433, 641, 622, 513, 919, 202, 543, 877, 665, 193, 1027, 2182, 195, 2484, 525, 2250, 1625, 1490, 1166, 168, 695, 297, 737, 1436, 5241, 2763, 2140, 1243, 1783, 1605, 2206, 2091, 3317, 1539, 845, 1366, 2111, 509, 1310, 471, 1998, 2100, 2138, 10497, 1098, 3574, 1326, 4187, 1630, 1885, 1620, 2539, 499, 1354, 2763, 795, 2204, 1275, 436, 1168, 1179, 864, 1209, 1214, 1771, 1121, 1164, 619, 494, 834, 1235, 1164, 1168, 897, 684, 1421, 1184, 1240, 193, 836, 1331, 2149, 1302, 1502, 191, 230, 3062, 494, 773, 742, 836, 272, 866, 1030, 207, 753, 710, 366, 659, 2027, 4735, 847], "count": 143344}